bsb_2025/__init__.py
bsb_2025/config.py
bsb_2025/core.py
bsb_2025/listener.py
bsb_2025-1.0.0.dist-info/licenses/LICENSE
bsb_2025-1.0.0.dist-info/METADATA
bsb_2025-1.0.0.dist-info/WHEEL
bsb_2025-1.0.0.dist-info/entry_points.txt
bsb_2025-1.0.0.dist-info/top_level.txt
bsb_2025-1.0.0.dist-info/RECORD
